plugin.cmake
setup.py
girder_hdfs_assetstore/__init__.py
girder_hdfs_assetstore/assetstore.py
girder_hdfs_assetstore/rest.py
girder_hdfs_assetstore.egg-info/PKG-INFO
girder_hdfs_assetstore.egg-info/SOURCES.txt
girder_hdfs_assetstore.egg-info/dependency_links.txt
girder_hdfs_assetstore.egg-info/entry_points.txt
girder_hdfs_assetstore.egg-info/not-zip-safe
girder_hdfs_assetstore.egg-info/requires.txt
girder_hdfs_assetstore.egg-info/top_level.txt
girder_hdfs_assetstore/web_client/constants.js
girder_hdfs_assetstore/web_client/main.js
girder_hdfs_assetstore/web_client/package.json
girder_hdfs_assetstore/web_client/routes.js
girder_hdfs_assetstore/web_client/models/AssetstoreModel.js
girder_hdfs_assetstore/web_client/stylesheets/hdfsAssetstoreImportView.styl
girder_hdfs_assetstore/web_client/templates/assetstoresViewImportButton.pug
girder_hdfs_assetstore/web_client/templates/assetstoresViewInfo.pug
girder_hdfs_assetstore/web_client/templates/editAssetstoreWidgetFields.pug
girder_hdfs_assetstore/web_client/templates/hdfsAssetstoreImportView.pug
girder_hdfs_assetstore/web_client/templates/newAssetstoreWidgetCreate.pug
girder_hdfs_assetstore/web_client/views/AssetstoresView.js
girder_hdfs_assetstore/web_client/views/EditAssetstoreWidget.js
girder_hdfs_assetstore/web_client/views/HdfsAssetstoreImportView.js
girder_hdfs_assetstore/web_client/views/NewAssetstoreWidget.js
plugin_tests/__init__.py
plugin_tests/hdfs_assetstore_test.py
plugin_tests/mock_fs/to_import/hello.txt
plugin_tests/mock_fs/to_import/world.txt