Metadata-Version: 1.2
Name: girder-hdfs-assetstore
Version: 2.0.0a1
Summary: This plugin adds a new assetstore type to the system that proxies files for the Hadoop Distributed Filesystem (HDFS). This also allows files on a pre-existing HDFS instance to be imported into the Girder data hierarchy.
Home-page: http://girder.readthedocs.io/en/latest/plugins.html#hdfs-assetstore
Author: Kitware, Inc.
Author-email: kitware@kitware.com
License: Apache 2.0
Platform: UNKNOWN
Classifier: Development Status :: 5 - Production/Stable
Classifier: Environment :: Web Environment
Classifier: License :: OSI Approved :: Apache Software License
Classifier: Operating System :: OS Independent
Classifier: Programming Language :: Python
Classifier: Programming Language :: Python :: 2
Classifier: Programming Language :: Python :: 2.7
Requires-Python: <3.0
